spl_transpiler-0.3.0.dist-info/METADATA
spl_transpiler-0.3.0.dist-info/WHEEL
spl_transpiler-0.3.0.dist-info/entry_points.txt
spl_transpiler-0.3.0.dist-info/licenses/LICENSE
spl_transpiler.libs/libgcc_s-1e52349c.so.1
spl_transpiler/live_translator.py
spl_transpiler/__main__.py
spl_transpiler/macros.py
spl_transpiler/utils.py
spl_transpiler/live_translator.tcss
spl_transpiler/__init__.py
spl_transpiler/spl_transpiler.abi3.so
spl_transpiler-0.3.0.dist-info/RECORD
