Metadata-Version: 2.4
Name: spl_transpiler
Version: 0.3.0
Classifier: Programming Language :: Rust
Classifier: Programming Language :: Python :: Implementation :: CPython
Classifier: Programming Language :: Python :: Implementation :: PyPy
Requires-Dist: pydantic>=2
Requires-Dist: textual[syntax]
Requires-Dist: pyperclip
Requires-Dist: pyspark~=4.0.0.dev2
Requires-Dist: pyspark-spl-tools
Requires-Dist: textual[syntax] ; extra == 'cli'
Requires-Dist: pyperclip ; extra == 'cli'
Provides-Extra: cli
License-File: LICENSE
Summary: Convert Splunk SPL queries into PySpark code
Requires-Python: >=3.10
